eldar_transaction_race/__init__.py
eldar_transaction_race/game.py
eldar_transaction_race/words.py
eldar_translation_race-1.0.0.dist-info/METADATA
eldar_translation_race-1.0.0.dist-info/WHEEL
eldar_translation_race-1.0.0.dist-info/entry_points.txt
eldar_translation_race-1.0.0.dist-info/top_level.txt
eldar_translation_race-1.0.0.dist-info/RECORD
