Metadata-Version: 2.4
Name: eldar-translation-race
Version: 1.0.0
Summary: CLI Translation Race Game (Tərcümə Yarışı)
Author: Eldar
Requires-Python: >=3.8
